{
  "formatVersion": "1.1",
  "component": {
    "group": "xyz.canardoux",
    "module": "tau_core",
    "version": "8.1.0",
    "attributes": {
      "org.gradle.status": "release"
    }
  },
  "createdBy": {
    "gradle": {
      "version": "6.7.1",
      "buildId": "u43aanme5nda5efyz7qvvocgee"
    }
  },
  "variants": [
    {
      "name": "releaseApiPublication",
      "attributes": {
        "org.gradle.category": "library",
        "org.gradle.dependency.bundling": "external",
        "org.gradle.libraryelements": "aar",
        "org.gradle.usage": "java-api"
      },
      "files": [
        {
          "name": "tau_core-8.1.0.aar",
          "url": "tau_core-8.1.0.aar",
          "size": 1319349,
          "sha512": "dfcf3abf44ca1a1fc9b1d665e01d943cb98429cfa291a643a4627c9c34db2d8f925c1967333e7fc6973ccc689b9e9f7266971d841b9da9d418bea1f72be7168c",
          "sha256": "62a9242ee1d6cdf123bc2819f97261e4236eec5485ab70e7d064924bfe9c71d1",
          "sha1": "ea3c7ed0081b55dd0ef4090d41b5860252f15dfb",
          "md5": "63f438291c1af6129fc79613be56a70e"
        }
      ]
    },
    {
      "name": "releaseRuntimePublication",
      "attributes": {
        "org.gradle.category": "library",
        "org.gradle.dependency.bundling": "external",
        "org.gradle.libraryelements": "aar",
        "org.gradle.usage": "java-runtime"
      },
      "dependencies": [
        {
          "group": "androidx.core",
          "module": "core",
          "version": {
            "requires": "1.3.2"
          }
        },
        {
          "group": "androidx.media",
          "module": "media",
          "version": {
            "requires": "1.2.0"
          }
        },
        {
          "group": "androidx.appcompat",
          "module": "appcompat",
          "version": {
            "requires": "1.2.0"
          }
        }
      ],
      "files": [
        {
          "name": "tau_core-8.1.0.aar",
          "url": "tau_core-8.1.0.aar",
          "size": 1319349,
          "sha512": "dfcf3abf44ca1a1fc9b1d665e01d943cb98429cfa291a643a4627c9c34db2d8f925c1967333e7fc6973ccc689b9e9f7266971d841b9da9d418bea1f72be7168c",
          "sha256": "62a9242ee1d6cdf123bc2819f97261e4236eec5485ab70e7d064924bfe9c71d1",
          "sha1": "ea3c7ed0081b55dd0ef4090d41b5860252f15dfb",
          "md5": "63f438291c1af6129fc79613be56a70e"
        }
      ]
    }
  ]
}
